rdf_shacl_generator/__init__.py
rdf_shacl_generator/rdf_graph_generator.py
rdf_shacl_generator/script.py
rdf_shacl_generator/shacl_mapping_generator.py
rdf_shacl_generator/value_generators.py
rdf_shacl_generator/datasets/book_awards.csv
rdf_shacl_generator/datasets/book_genre.csv
rdf_shacl_generator/datasets/book_titles.csv
rdf_shacl_generator/datasets/female_first_name.csv
rdf_shacl_generator/datasets/job_title.csv
rdf_shacl_generator/datasets/male_first_name.csv
rdf_shacl_generator/datasets/movie_awards.csv
rdf_shacl_generator/datasets/movie_genre.csv
rdf_shacl_generator/datasets/movie_titles.csv
rdf_shacl_generator/datasets/street_name.csv
rdf_shacl_generator/datasets/surnames.csv
rdf_shacl_generator/datasets/tvseries_titles.csv
rdf_shacl_generator-1.0.8.dist-info/LICENSE
rdf_shacl_generator-1.0.8.dist-info/METADATA
rdf_shacl_generator-1.0.8.dist-info/WHEEL
rdf_shacl_generator-1.0.8.dist-info/entry_points.txt
rdf_shacl_generator-1.0.8.dist-info/top_level.txt
rdf_shacl_generator-1.0.8.dist-info/RECORD
