Metadata-Version: 2.1
Name: rdf-shacl-generator
Version: 1.0.8
Summary: Synthetic RDF graph generator based on SHACL constraints.
Home-page: UNKNOWN
License: UNKNOWN
Platform: UNKNOWN
Requires-Dist: rdflib >=7.0.0
Requires-Dist: python-dateutil >=2.8.2
Requires-Dist: exrex >=0.11.0
Requires-Dist: setuptools >=69.1.1
